cf_remote/VERSION
cf_remote/__init__.py
cf_remote/__main__.py
cf_remote/aramid.py
cf_remote/cloud_data.py
cf_remote/commands.py
cf_remote/demo.py
cf_remote/log.py
cf_remote/main.py
cf_remote/packages.py
cf_remote/paths.py
cf_remote/remote.py
cf_remote/spawn.py
cf_remote/ssh.py
cf_remote/utils.py
cf_remote/version.py
cf_remote/web.py
tests/__init__.py
tests/test_cache.py
tests/test_packages.py
tests/test_ssh.py
cf_remote_x-0.1.15.dist-info/LICENSE
cf_remote_x-0.1.15.dist-info/METADATA
cf_remote_x-0.1.15.dist-info/WHEEL
cf_remote_x-0.1.15.dist-info/entry_points.txt
cf_remote_x-0.1.15.dist-info/top_level.txt
cf_remote_x-0.1.15.dist-info/RECORD
