Metadata-Version: 2.1
Name: cf-remote-x
Version: 0.1.15
Summary: Tooling to deploy CFEngine (and much more)
Home-page: https://github.com/cfengine/cf-remote-x
Author: Northern.tech, Inc.
Author-email: contact@northern.tech
Classifier: Programming Language :: Python :: 3
Classifier: License :: OSI Approved :: GNU General Public License v3 (GPLv3)
Classifier: Operating System :: OS Independent
Requires-Python: >=3.5
License-File: LICENSE
Requires-Dist: requests (>=2.25.1)
Requires-Dist: apache-libcloud (>=3.3.1)
